nonebot_plugin_imagetools/__init__.py
nonebot_plugin_imagetools/color_table.py
nonebot_plugin_imagetools/command.py
nonebot_plugin_imagetools/config.py
nonebot_plugin_imagetools/functions.py
nonebot_plugin_imagetools/utils.py
nonebot_plugin_imagetools-0.5.1.dist-info/LICENSE
nonebot_plugin_imagetools-0.5.1.dist-info/METADATA
nonebot_plugin_imagetools-0.5.1.dist-info/WHEEL
nonebot_plugin_imagetools-0.5.1.dist-info/RECORD
